[{
        "id": "1",
        "name": "Đoàn Hải Long",
        "avatar": "https://scontent.fhan14-2.fna.fbcdn.net/v/t39.30808-1/269693668_1792401901149374_7750707019832737753_n.jpg?stp=dst-jpg_p240x240&_nc_cat=103&ccb=1-5&_nc_sid=7206a8&_nc_ohc=p67-BSe4Hm4AX_Ihz_4&_nc_ht=scontent.fhan14-2.fna&oh=00_AT_Z2r_9Q5QK2bQsnN7mCbeV9AQpGYjTFCb_XaTXjRsa2w&oe=6223C29E",
        "age": 22,
        "description": "thân thiện , hoc hỏi nhanh",
        "programmingLanguage": ["JS", "JAVA"],
        "gender": "Nam",
        "type": "ADMIN"
    },
    {
        "id": "2",
        "name": "Trần Quỳnh Giang",
        "avatar": "https://scontent.fhan14-2.fna.fbcdn.net/v/t39.30808-6/217508138_544911016924410_3347837634667130412_n.jpg?_nc_cat=111&ccb=1-5&_nc_sid=174925&_nc_ohc=EJJhc4DHsGIAX-1Uz1C&_nc_ht=scontent.fhan14-2.fna&oh=00_AT8_5UvFr8y7K6f8FxrvpGCfImp2f_L0KV6N3fYz3kC24g&oe=6223B73E",
        "age": 24,
        "description": "thân thiện , tốt bụng",
        "programmingLanguage": ["PHP", "C#"],
        "gender": "Nữ",
        "type": "CLIENT"
    }
]